ramda/And.py
ramda/F.py
ramda/Is.py
ramda/Max.py
ramda/Min.py
ramda/Not.py
ramda/Or.py
ramda/T.py
ramda/__.py
ramda/__init__.py
ramda/add.py
ramda/adjust.py
ramda/all.py
ramda/always.py
ramda/any.py
ramda/ap.py
ramda/append.py
ramda/apply.py
ramda/assoc.py
ramda/assocPath.py
ramda/binary.py
ramda/chain.py
ramda/clone.py
ramda/comparator.py
ramda/compose.py
ramda/concat.py
ramda/cond.py
ramda/construct.py
ramda/constructN.py
ramda/converge.py
ramda/countBy.py
ramda/curry.py
ramda/curryN.py
ramda/defaultTo.py
ramda/difference.py
ramda/differenceWith.py
ramda/divide.py
ramda/drop.py
ramda/empty.py
ramda/eqProps.py
ramda/equals.py
ramda/filter.py
ramda/find.py
ramda/findIndex.py
ramda/findLast.py
ramda/findLastIndex.py
ramda/flatten.py
ramda/flip.py
ramda/forEach.py
ramda/fromPairs.py
ramda/groupBy.py
ramda/gt.py
ramda/gte.py
ramda/has.py
ramda/hasIn.py
ramda/hasPath.py
ramda/head.py
ramda/identity.py
ramda/ifElse.py
ramda/inc.py
ramda/indexOf.py
ramda/insert.py
ramda/intersection.py
ramda/into.py
ramda/invoker.py
ramda/isEmpty.py
ramda/isNil.py
ramda/join.py
ramda/juxt.py
ramda/keys.py
ramda/keysIn.py
ramda/last.py
ramda/lastIndexOf.py
ramda/length.py
ramda/lens.py
ramda/lensIndex.py
ramda/lensPath.py
ramda/lensProp.py
ramda/lift.py
ramda/liftN.py
ramda/lt.py
ramda/lte.py
ramda/map.py
ramda/match.py
ramda/mathMod.py
ramda/maxBy.py
ramda/minBy.py
ramda/modulo.py
ramda/multiply.py
ramda/nAry.py
ramda/nth.py
ramda/objOf.py
ramda/of.py
ramda/omit.py
ramda/once.py
ramda/over.py
ramda/partition.py
ramda/path.py
ramda/pathEq.py
ramda/paths.py
ramda/pick.py
ramda/pickAll.py
ramda/pickBy.py
ramda/pipe.py
ramda/pluck.py
ramda/prepend.py
ramda/product.py
ramda/project.py
ramda/prop.py
ramda/propEq.py
ramda/propOr.py
ramda/props.py
ramda/range.py
ramda/reduce.py
ramda/reduceBy.py
ramda/reduceRight.py
ramda/reduced.py
ramda/reject.py
ramda/remove.py
ramda/repeat.py
ramda/replace.py
ramda/reverse.py
ramda/set.py
ramda/slice.py
ramda/sort.py
ramda/sortBy.py
ramda/split.py
python_ramda-0.8.0.dist-info/LICENSE
python_ramda-0.8.0.dist-info/METADATA
python_ramda-0.8.0.dist-info/WHEEL
python_ramda-0.8.0.dist-info/top_level.txt
python_ramda-0.8.0.dist-info/RECORD
