Metadata-Version: 2.1
Name: python_ramda
Version: 0.8.0
Summary: A small clone of ramda
Home-page: https://github.com/zydmayday/python_ramda
Author-email: zydmayday@gmail.com
Keywords: functional programming,ramda
Classifier: License :: OSI Approved :: MIT License
Classifier: Intended Audience :: Developers
Classifier: Programming Language :: Python
Classifier: Programming Language :: Python :: 3.6
Classifier: Programming Language :: Python :: 3.7
Classifier: Programming Language :: Python :: 3.8
Classifier: Programming Language :: Python :: 3.9
Classifier: Programming Language :: Python :: 3.10
License-File: LICENSE
